yta_audio_narration_tiktok/__init__.py
yta_audio_narration_tiktok-0.0.3.dist-info/LICENSE
yta_audio_narration_tiktok-0.0.3.dist-info/METADATA
yta_audio_narration_tiktok-0.0.3.dist-info/WHEEL
yta_audio_narration_tiktok-0.0.3.dist-info/RECORD
