Metadata-Version: 2.3
Name: yta-audio-narration-tiktok
Version: 0.0.3
Summary: Youtube Autonomous Audio Narration Tiktok Voice Module.
Author: danialcala94
Author-email: danielalcalavalera@gmail.com
Requires-Python: ==3.9
Classifier: Programming Language :: Python :: 3
Classifier: Programming Language :: Python :: 3.9
Requires-Dist: requests (>=2.32.3,<9.0.0)
Requires-Dist: yta_audio_narration_common (>=0.0.1,<1.0.0)
Requires-Dist: yta_constants (>=0.0.1,<1.0.0)
Requires-Dist: yta_file (>=0.0.1,<1.0.0)
Requires-Dist: yta_programming (>=0.0.1,<1.0.0)
Requires-Dist: yta_text (>=0.0.1,<1.0.0)
